CHANGES.rst
CONTRIBUTORS.rst
DEVELOP.rst
LICENSE.rst
MANIFEST.in
README.rst
setup.cfg
setup.py
docs/index.rst
src/jazkarta/__init__.py
src/jazkarta.abtesttile.egg-info/PKG-INFO
src/jazkarta.abtesttile.egg-info/SOURCES.txt
src/jazkarta.abtesttile.egg-info/dependency_links.txt
src/jazkarta.abtesttile.egg-info/entry_points.txt
src/jazkarta.abtesttile.egg-info/namespace_packages.txt
src/jazkarta.abtesttile.egg-info/not-zip-safe
src/jazkarta.abtesttile.egg-info/requires.txt
src/jazkarta.abtesttile.egg-info/top_level.txt
src/jazkarta/abtesttile/__init__.py
src/jazkarta/abtesttile/configure.zcml
src/jazkarta/abtesttile/interfaces.py
src/jazkarta/abtesttile/permissions.zcml
src/jazkarta/abtesttile/setuphandlers.py
src/jazkarta/abtesttile/testing.py
src/jazkarta/abtesttile/tile.py
src/jazkarta/abtesttile/upgrades.py
src/jazkarta/abtesttile/upgrades.zcml
src/jazkarta/abtesttile/locales/jazkarta.abtesttile.pot
src/jazkarta/abtesttile/locales/update.sh
src/jazkarta/abtesttile/profiles/default/browserlayer.xml
src/jazkarta/abtesttile/profiles/default/metadata.xml
src/jazkarta/abtesttile/profiles/default/registry.xml
src/jazkarta/abtesttile/profiles/default/rolemap.xml
src/jazkarta/abtesttile/profiles/uninstall/browserlayer.xml
src/jazkarta/abtesttile/profiles/uninstall/registry.xml
src/jazkarta/abtesttile/templates/abtesttile.pt
src/jazkarta/abtesttile/tests/__init__.py
src/jazkarta/abtesttile/tests/test_setup.py