Metadata-Version: 1.1
Name: jazkarta.abtesttile
Version: 1.0
Summary: Plone Mosaic Tile for A/B Testing content changes
Home-page: https://pypi.python.org/pypi/jazkarta.abtesttile
Author: jazkarta
Author-email: info@jazkarta.com
License: GPL version 2
Keywords: Python Plone analytics
Platform: UNKNOWN
Classifier: Environment :: Web Environment
Classifier: Framework :: Plone
Classifier: Framework :: Plone :: 4.3
Classifier: Framework :: Plone :: 5.0
Classifier: Framework :: Plone :: 5.1
Classifier: Programming Language :: Python
Classifier: Programming Language :: Python :: 2.7
Classifier: Operating System :: OS Independent
Classifier: License :: OSI Approved :: GNU General Public License v2 (GPLv2)
